metaphor_python/__init__.py
metaphor_python/api.py
metaphor_python/metaphor.py
metaphor_python-0.1.23.dist-info/METADATA
metaphor_python-0.1.23.dist-info/WHEEL
metaphor_python-0.1.23.dist-info/top_level.txt
metaphor_python-0.1.23.dist-info/RECORD
