Metadata-Version: 2.1
Name: metaphor-python
Version: 0.1.23
Summary: A Python package for the Metaphor API.
Home-page: https://github.com/metaphorsystems/metaphor-python
Author: Metaphor
Author-email: hello@metaphor.systems
Classifier: Development Status :: 3 - Alpha
Classifier: Intended Audience :: Developers
Classifier: License :: OSI Approved :: MIT License
Classifier: Programming Language :: Python :: 3
Classifier: Programming Language :: Python :: 3.6
Classifier: Programming Language :: Python :: 3.7
Classifier: Programming Language :: Python :: 3.8
Classifier: Programming Language :: Python :: 3.9
